porunga_cli/__init__.py
porunga_cli/cli.py
porunga_cli/llm.py
porunga_cli/utils/__init__.py
porunga_cli/utils/examples/__init__.py
porunga_cli/utils/examples/few_shot_examples.py
porunga_cli/utils/exceptions/parse_error.py
porunga_cli/utils/parse_messages.py
porunga_cli/utils/schema/__init__.py
porunga_cli-0.1.2.dist-info/METADATA
porunga_cli-0.1.2.dist-info/WHEEL
porunga_cli-0.1.2.dist-info/entry_points.txt
porunga_cli-0.1.2.dist-info/RECORD
