Metadata-Version: 2.1
Name: porunga_cli
Version: 0.1.2
Summary: A CLI tool to suggest commit messages
Author: HARIHARA SUDHAN (HARI)
Author-email: 108145682+hari0205@users.noreply.github.com
Requires-Python: >=3.11,<4.0
Classifier: Programming Language :: Python :: 3
Classifier: Programming Language :: Python :: 3.11
Classifier: Programming Language :: Python :: 3.12
Requires-Dist: click (>=8.1.7,<9.0.0)
Requires-Dist: defusedxml (>=0.7.1,<0.8.0)
Requires-Dist: flake8 (>=7.1.0,<8.0.0)
Requires-Dist: inquirerpy (>=0.3.4,<0.4.0)
Requires-Dist: keyring (>=25.2.1,<26.0.0)
Requires-Dist: keyrings-alt (>=5.0.1,<6.0.0)
Requires-Dist: langchain (>=0.1.16,<0.2.0)
Requires-Dist: langchain-openai (>=0.1.3,<0.2.0)
Requires-Dist: python-dotenv (>=1.0.1,<2.0.0)
Requires-Dist: tenacity (>=8.4.2,<9.0.0)
